prometheus_alert_model/__init__.py
prometheus_alert_model/main.py
prometheus_alert_model/utils.py
prometheus_alert_model_leo-1.1.0.dist-info/LICENSE
prometheus_alert_model_leo-1.1.0.dist-info/METADATA
prometheus_alert_model_leo-1.1.0.dist-info/WHEEL
prometheus_alert_model_leo-1.1.0.dist-info/RECORD
