Metadata-Version: 2.1
Name: prometheus-alert-model-leo
Version: 1.1.0
Summary: Pydantic model of the Prometheus Alertmanager alert payload
Home-page: https://github.com/trallnag/prometheus-alert-model-for-python
License: Apache-2.0
Keywords: prometheus,alertmanager,alerting,pydantic
Author: Tim Schwenke
Author-email: tim.and.trallnag+code@gmail.com
Requires-Python: >=3.8,<4.0
Classifier: License :: OSI Approved :: Apache Software License
Classifier: Programming Language :: Python :: 3
Classifier: Programming Language :: Python :: 3.8
Classifier: Programming Language :: Python :: 3.9
Classifier: Programming Language :: Python :: 3.10
Classifier: Programming Language :: Python :: 3.11
Requires-Dist: pydantic
Requires-Dist: typing-extensions
Project-URL: Repository, https://github.com/trallnag/prometheus-alert-model-for-python
